{
    "Message": "",
    "OtherInfo": {},
    "Result": {
        "gsjlr": [
            {
                "ratio": "109.32",
                "value": "741956223.82",
                "year": "2016A"
            },
            {
                "ratio": "13.50",
                "value": "842125454.55",
                "year": "2017E"
            },
            {
                "ratio": "34.85",
                "value": "1135623636.36",
                "year": "2018E"
            },
            {
                "ratio": "28.62",
                "value": "1460690909.09",
                "year": "2019E"
            }
        ],
        "jgyc": {
            "baseYear": 2016,
            "data": [
                {
                    "jgmc": "六个月平均",
                    "sy": "2.04",
                    "sy1": "2.05",
                    "sy2": "2.79",
                    "sy3": "3.58",
                    "syl": "34.33",
                    "syl1": "31.32",
                    "syl2": "22.89",
                    "syl3": "17.88"
                },
                {
                    "jgmc": "广证恒生",
                    "sy": "2.04",
                    "sy1": "1.92",
                    "sy2": "2.73",
                    "sy3": "3.47",
                    "syl": "34.33",
                    "syl1": "33.22",
                    "syl2": "23.35",
                    "syl3": "18.39"
                },
                {
                    "jgmc": "申万宏源",
                    "sy": "2.04",
                    "sy1": "1.96",
                    "sy2": "2.71",
                    "sy3": "3.55",
                    "syl": "34.33",
                    "syl1": "32.64",
                    "syl2": "23.56",
                    "syl3": "17.99"
                },
                {
                    "jgmc": "华金证券",
                    "sy": "2.04",
                    "sy1": "1.94",
                    "sy2": "2.79",
                    "sy3": "3.26",
                    "syl": "34.33",
                    "syl1": "32.96",
                    "syl2": "22.86",
                    "syl3": "19.61"
                },
                {
                    "jgmc": "中信证券",
                    "sy": "2.04",
                    "sy1": "2.00",
                    "sy2": "2.73",
                    "sy3": "3.66",
                    "syl": "34.33",
                    "syl1": "31.88",
                    "syl2": "23.40",
                    "syl3": "17.43"
                },
                {
                    "jgmc": "西南证券",
                    "sy": "2.04",
                    "sy1": "2.11",
                    "sy2": "2.87",
                    "sy3": "3.86",
                    "syl": "34.33",
                    "syl1": "30.20",
                    "syl2": "22.28",
                    "syl3": "16.54"
                },
                {
                    "jgmc": "民生证券",
                    "sy": "2.04",
                    "sy1": "2.38",
                    "sy2": "3.06",
                    "sy3": "3.85",
                    "syl": "34.33",
                    "syl1": "26.83",
                    "syl2": "20.87",
                    "syl3": "16.59"
                },
                {
                    "jgmc": "东北证券",
                    "sy": "2.04",
                    "sy1": "2.03",
                    "sy2": "2.67",
                    "sy3": "3.44",
                    "syl": "34.33",
                    "syl1": "31.49",
                    "syl2": "23.89",
                    "syl3": "18.59"
                }
            ]
        },
        "jzcsyl": [
            {
                "ratio": "-",
                "value": "74.94",
                "year": "2016A"
            },
            {
                "ratio": "-",
                "value": "36.15",
                "year": "2017E"
            },
            {
                "ratio": "-",
                "value": "37.02",
                "year": "2018E"
            },
            {
                "ratio": "-",
                "value": "36.65",
                "year": "2019E"
            }
        ],
        "mgsy": [
            {
                "ratio": "109.32",
                "value": "1.83",
                "year": "2016A"
            },
            {
                "ratio": "14.85",
                "value": "2.10",
                "year": "2017E"
            },
            {
                "ratio": "34.94",
                "value": "2.83",
                "year": "2018E"
            },
            {
                "ratio": "28.62",
                "value": "3.64",
                "year": "2019E"
            }
        ],
        "pjtj": [
            {
                "jc": "0",
                "mc": "0",
                "mr": "1",
                "pjxs": "4.50",
                "sjd": "1月内",
                "zc": "1",
                "zhpj": "买入",
                "zjs": "2",
                "zx": "0"
            },
            {
                "jc": "0",
                "mc": "0",
                "mr": "1",
                "pjxs": "4.50",
                "sjd": "2月内",
                "zc": "1",
                "zhpj": "买入",
                "zjs": "2",
                "zx": "0"
            },
            {
                "jc": "0",
                "mc": "0",
                "mr": "1",
                "pjxs": "4.50",
                "sjd": "3月内",
                "zc": "1",
                "zhpj": "买入",
                "zjs": "2",
                "zx": "0"
            },
            {
                "jc": "0",
                "mc": "0",
                "mr": "2",
                "pjxs": "4.29",
                "sjd": "6月内",
                "zc": "5",
                "zhpj": "买入",
                "zjs": "7",
                "zx": "0"
            },
            {
                "jc": "0",
                "mc": "0",
                "mr": "4",
                "pjxs": "4.33",
                "sjd": "1年内",
                "zc": "8",
                "zhpj": "买入",
                "zjs": "12",
                "zx": "0"
            }
        ],
        "ycmx": {
            "jlr": {
                "baseYear": 2016,
                "data": [
                    {
                        "jg": "广证恒生",
                        "pj": "买入",
                        "sj": "2018-01-22",
                        "value": "7.42亿",
                        "value1": "7.81亿",
                        "value2": "11.1亿",
                        "value3": "14.1亿",
                        "value4": "--",
                        "value5": "--",
                        "yjy": "肖明亮,叶锟"
                    },
                    {
                        "jg": "申万宏源",
                        "pj": "增持",
                        "sj": "2018-01-12",
                        "value": "7.42亿",
                        "value1": "7.95亿",
                        "value2": "11.0亿",
                        "value3": "14.4亿",
                        "value4": "--",
                        "value5": "--",
                        "yjy": "马晓天"
                    },
                    {
                        "jg": "中信证券",
                        "pj": "--",
                        "sj": "2017-11-13",
                        "value": "7.42亿",
                        "value1": "8.14亿",
                        "value2": "11.1亿",
                        "value3": "14.9亿",
                        "value4": "--",
                        "value5": "--",
                        "yjy": "姜娅"
                    },
                    {
                        "jg": "华金证券",
                        "pj": "增持",
                        "sj": "2017-11-01",
                        "value": "7.42亿",
                        "value1": "7.87亿",
                        "value2": "11.3亿",
                        "value3": "13.2亿",
                        "value4": "--",
                        "value5": "--",
                        "yjy": "蔡景彦"
                    },
                    {
                        "jg": "中信证券",
                        "pj": "增持",
                        "sj": "2017-10-30",
                        "value": "7.42亿",
                        "value1": "8.14亿",
                        "value2": "11.1亿",
                        "value3": "14.9亿",
                        "value4": "--",
                        "value5": "--",
                        "yjy": "姜娅"
                    },
                    {
                        "jg": "西南证券",
                        "pj": "增持",
                        "sj": "2017-10-30",
                        "value": "7.42亿",
                        "value1": "8.59亿",
                        "value2": "11.6亿",
                        "value3": "15.7亿",
                        "value4": "--",
                        "value5": "--",
                        "yjy": "朱芸"
                    },
                    {
                        "jg": "华金证券",
                        "pj": "增持",
                        "sj": "2017-08-22",
                        "value": "7.42亿",
                        "value1": "9.48亿",
                        "value2": "11.6亿",
                        "value3": "13.3亿",
                        "value4": "--",
                        "value5": "--",
                        "yjy": "蔡景彦"
                    },
                    {
                        "jg": "东北证券",
                        "pj": "增持",
                        "sj": "2017-08-21",
                        "value": "7.42亿",
                        "value1": "8.24亿",
                        "value2": "10.9亿",
                        "value3": "14.0亿",
                        "value4": "--",
                        "value5": "--",
                        "yjy": "唐凯,王朝宁"
                    },
                    {
                        "jg": "民生证券",
                        "pj": "买入",
                        "sj": "2017-08-21",
                        "value": "7.42亿",
                        "value1": "9.68亿",
                        "value2": "12.4亿",
                        "value3": "15.6亿",
                        "value4": "--",
                        "value5": "--",
                        "yjy": "郑平,胡独巍"
                    },
                    {
                        "jg": "西南证券",
                        "pj": "买入",
                        "sj": "2017-08-21",
                        "value": "7.42亿",
                        "value1": "8.59亿",
                        "value2": "11.6亿",
                        "value3": "15.7亿",
                        "value4": "--",
                        "value5": "--",
                        "yjy": "朱芸"
                    },
                    {
                        "jg": "中信证券",
                        "pj": "增持",
                        "sj": "2017-08-21",
                        "value": "7.42亿",
                        "value1": "8.14亿",
                        "value2": "11.1亿",
                        "value3": "14.9亿",
                        "value4": "--",
                        "value5": "--",
                        "yjy": "姜娅"
                    }
                ]
            },
            "mgsy": {
                "baseYear": 2016,
                "data": [
                    {
                        "jg": "广证恒生",
                        "pj": "买入",
                        "sj": "2018-01-22",
                        "value": "1.8261",
                        "value1": "2.15",
                        "value2": "3.06",
                        "value3": "3.89",
                        "value4": "--",
                        "value5": "--",
                        "yjy": "肖明亮,叶锟"
                    },
                    {
                        "jg": "申万宏源",
                        "pj": "增持",
                        "sj": "2018-01-12",
                        "value": "1.8261",
                        "value1": "1.96",
                        "value2": "2.71",
                        "value3": "3.55",
                        "value4": "--",
                        "value5": "--",
                        "yjy": "马晓天"
                    },
                    {
                        "jg": "中信证券",
                        "pj": "--",
                        "sj": "2017-11-13",
                        "value": "1.8261",
                        "value1": "2.02",
                        "value2": "2.75",
                        "value3": "3.69",
                        "value4": "--",
                        "value5": "--",
                        "yjy": "姜娅"
                    },
                    {
                        "jg": "华金证券",
                        "pj": "增持",
                        "sj": "2017-11-01",
                        "value": "1.8261",
                        "value1": "1.94",
                        "value2": "2.79",
                        "value3": "3.26",
                        "value4": "--",
                        "value5": "--",
                        "yjy": "蔡景彦"
                    },
                    {
                        "jg": "中信证券",
                        "pj": "增持",
                        "sj": "2017-10-30",
                        "value": "1.8261",
                        "value1": "2.02",
                        "value2": "2.75",
                        "value3": "3.69",
                        "value4": "--",
                        "value5": "--",
                        "yjy": "姜娅"
                    },
                    {
                        "jg": "西南证券",
                        "pj": "增持",
                        "sj": "2017-10-30",
                        "value": "1.8261",
                        "value1": "2.11",
                        "value2": "2.87",
                        "value3": "3.86",
                        "value4": "--",
                        "value5": "--",
                        "yjy": "朱芸"
                    },
                    {
                        "jg": "华金证券",
                        "pj": "增持",
                        "sj": "2017-08-22",
                        "value": "1.8261",
                        "value1": "2.33",
                        "value2": "2.85",
                        "value3": "3.26",
                        "value4": "--",
                        "value5": "--",
                        "yjy": "蔡景彦"
                    },
                    {
                        "jg": "东北证券",
                        "pj": "增持",
                        "sj": "2017-08-21",
                        "value": "1.8261",
                        "value1": "2.03",
                        "value2": "2.67",
                        "value3": "3.44",
                        "value4": "--",
                        "value5": "--",
                        "yjy": "唐凯,王朝宁"
                    },
                    {
                        "jg": "民生证券",
                        "pj": "买入",
                        "sj": "2017-08-21",
                        "value": "1.8261",
                        "value1": "2.38",
                        "value2": "3.06",
                        "value3": "3.85",
                        "value4": "--",
                        "value5": "--",
                        "yjy": "郑平,胡独巍"
                    },
                    {
                        "jg": "西南证券",
                        "pj": "买入",
                        "sj": "2017-08-21",
                        "value": "1.8261",
                        "value1": "2.11",
                        "value2": "2.87",
                        "value3": "3.86",
                        "value4": "--",
                        "value5": "--",
                        "yjy": "朱芸"
                    },
                    {
                        "jg": "中信证券",
                        "pj": "增持",
                        "sj": "2017-08-21",
                        "value": "1.8261",
                        "value1": "2.02",
                        "value2": "2.75",
                        "value3": "3.69",
                        "value4": "--",
                        "value5": "--",
                        "yjy": "姜娅"
                    }
                ]
            }
        },
        "yctj": {
            "data": [
                {
                    "jlr": "2.26亿",
                    "jzcsyl": "52.11",
                    "mgjzc": "1.4500",
                    "mgsy": "0.5559",
                    "rq": "2014年",
                    "syycmgsy": "0.5559",
                    "yylr": "2.44亿",
                    "yyzsr": "43.1亿"
                },
                {
                    "jlr": "3.54亿",
                    "jzcsyl": "54.65",
                    "mgjzc": "2.2400",
                    "mgsy": "0.8724",
                    "rq": "2015年",
                    "syycmgsy": "0.8724",
                    "yylr": "3.80亿",
                    "yyzsr": "60.0亿"
                },
                {
                    "jlr": "7.42亿",
                    "jzcsyl": "74.94",
                    "mgjzc": "3.4296",
                    "mgsy": "1.8261",
                    "rq": "2016年",
                    "syycmgsy": "1.8261",
                    "yylr": "8.23亿",
                    "yyzsr": "82.4亿"
                },
                {
                    "jlr": "8.42亿(11家)",
                    "jzcsyl": "36.15(11家)",
                    "mgjzc": "6.0843(7家)",
                    "mgsy": "2.0973(11家)",
                    "rq": "2017年预测",
                    "syycmgsy": "2.0927(11家)",
                    "yylr": "9.43亿(9家)",
                    "yyzsr": "104亿(11家)"
                },
                {
                    "jlr": "11.4亿(11家)",
                    "jzcsyl": "37.02(11家)",
                    "mgjzc": "8.0414(7家)",
                    "mgsy": "2.8300(11家)",
                    "rq": "2018年预测",
                    "syycmgsy": "2.7891(11家)",
                    "yylr": "12.8亿(9家)",
                    "yyzsr": "129亿(11家)"
                },
                {
                    "jlr": "14.6亿(11家)",
                    "jzcsyl": "36.65(11家)",
                    "mgjzc": "10.5157(7家)",
                    "mgsy": "3.6400(11家)",
                    "rq": "2019年预测",
                    "syycmgsy": "3.5764(11家)",
                    "yylr": "16.4亿(9家)",
                    "yyzsr": "161亿(11家)"
                },
                {
                    "jlr": "--",
                    "jzcsyl": "--",
                    "mgjzc": "--",
                    "mgsy": "--",
                    "rq": "2020年预测",
                    "syycmgsy": "--",
                    "yylr": "--",
                    "yyzsr": "--"
                },
                {
                    "jlr": "--",
                    "jzcsyl": "--",
                    "mgjzc": "--",
                    "mgsy": "--",
                    "rq": "2021年预测",
                    "syycmgsy": "--",
                    "yylr": "--",
                    "yyzsr": "--"
                }
            ],
            "title": "2014、2015、2016"
        },
        "yysr": [
            {
                "ratio": "37.39",
                "value": "8237941601.99",
                "year": "2016A"
            },
            {
                "ratio": "25.72",
                "value": "10356850909.09",
                "year": "2017E"
            },
            {
                "ratio": "24.66",
                "value": "12910740000.00",
                "year": "2018E"
            },
            {
                "ratio": "24.60",
                "value": "16086505454.55",
                "year": "2019E"
            }
        ]
    },
    "Status": 0
}